[{"pk": 1, "model": "sitetree.tree", "fields": {"alias": "main", "title": "PyCon"}}, {"pk": 1, "model": "sitetree.treeitem", "fields": {"parent": null, "access_restricted": false, "access_permissions": [], "description": "", "insitetree": true, "hint": "", "url": "#", "inbreadcrumbs": true, "title": "Home", "tree": 1, "access_perm_type": 1, "alias": null, "sort_order": 1, "inmenu": true, "access_loggedin": false, "hidden": false, "urlaspattern": false}}, {"pk": 2, "model": "sitetree.treeitem", "fields": {"parent": null, "access_restricted": false, "access_permissions": [], "description": "", "insitetree": true, "hint": "", "url": "#", "inbreadcrumbs": true, "title": "Blog", "tree": 1, "access_perm_type": 1, "alias": null, "sort_order": 2, "inmenu": true, "access_loggedin": false, "hidden": false, "urlaspattern": false}}, {"pk": 3, "model": "sitetree.treeitem", "fields": {"parent": null, "access_restricted": false, "access_permissions": [], "description": "", "insitetree": true, "hint": "", "url": "#", "inbreadcrumbs": true, "title": "Registration", "tree": 1, "access_perm_type": 1, "alias": null, "sort_order": 3, "inmenu": true, "access_loggedin": false, "hidden": false, "urlaspattern": false}}, {"pk": 4, "model": "sitetree.treeitem", "fields": {"parent": null, "access_restricted": false, "access_permissions": [], "description": "", "insitetree": true, "hint": "", "url": "#", "inbreadcrumbs": true, "title": "Schedule", "tree": 1, "access_perm_type": 1, "alias": null, "sort_order": 4, "inmenu": true, "access_loggedin": false, "hidden": false, "urlaspattern": false}}, {"pk": 5, "model": "sitetree.treeitem", "fields": {"parent": null, "access_restricted": false, "access_permissions": [], "description": "", "insitetree": true, "hint": "", "url": "#", "inbreadcrumbs": true, "title": "Sponsors", "tree": 1, "access_perm_type": 1, "alias": null, "sort_order": 5, "inmenu": true, "access_loggedin": false, "hidden": false, "urlaspattern": false}}, {"pk": 6, "model": "sitetree.treeitem", "fields": {"parent": null, "access_restricted": false, "access_permissions": [], "description": "", "insitetree": true, "hint": "", "url": "#", "inbreadcrumbs": true, "title": "Venue", "tree": 1, "access_perm_type": 1, "alias": null, "sort_order": 6, "inmenu": true, "access_loggedin": false, "hidden": false, "urlaspattern": false}}]